createsend/__init__.py
createsend/administrator.py
createsend/cacert.pem
createsend/campaign.py
createsend/client.py
createsend/createsend.py
createsend/journey.py
createsend/journey_email.py
createsend/list.py
createsend/person.py
createsend/segment.py
createsend/subscriber.py
createsend/template.py
createsend/transactional.py
createsend/utils.py
createsend-9.1.4.dist-info/licenses/LICENSE
createsend-9.1.4.dist-info/METADATA
createsend-9.1.4.dist-info/WHEEL
createsend-9.1.4.dist-info/top_level.txt
createsend-9.1.4.dist-info/RECORD
